MANIFEST.in
README.rst
setup.py
D3GB/__init__.py
D3GB/genomebrowser.py
D3GB/utils.py
D3GB.egg-info/PKG-INFO
D3GB.egg-info/SOURCES.txt
D3GB.egg-info/dependency_links.txt
D3GB.egg-info/not-zip-safe
D3GB.egg-info/top_level.txt
D3GB/assemblies/GRCh37.bands.json
D3GB/assemblies/GRCh37.json
D3GB/assemblies/GRCh38.bands.json
D3GB/assemblies/GRCh38.json
D3GB/assemblies/NCBI36.json
D3GB/www/d3.min.js
D3GB/www/functions.js
D3GB/www/genomebrowser.js
D3GB/www/genomemap.js
D3GB/www/images.js
D3GB/www/jspdf.min.js
D3GB/www/query.js
D3GB/www/query.php
D3GB/www/sql.js
D3GB/www/template.html