Metadata-Version: 1.1
Name: D3GB
Version: 1.1
Summary: Creates an interactive genome browser with python
Home-page: http://d3gb.usal.es/
Author: Carlos Prieto, David Barrios
Author-email: bioinfo@usal.com
License: CC BY-NC-SA 4.0
Keywords: genome browser d3
Platform: UNKNOWN
Classifier: Development Status :: 5 - Production/Stable
Classifier: License :: Free for non-commercial use
Classifier: Programming Language :: Python :: 3
Classifier: Topic :: Scientific/Engineering :: Bio-Informatics
